{"XonpPcSankLQn5E7URpwZA==":"logo.svg","E8f7XegTeF6015sTdmDFtQ==":"group%2085-1512x631.png","sEQRV4Oub0JQEU9/jsz1mw==":"group%2086-1512x3419.png","uEkvRy8RxaK8docZKXWTkg==":"taste1.svg","Uare4t2TW1d05PNJPM0W7g==":"group%2086-1512x3419.png","SMin/akQ0vHRMrO9da2/BA==":"strawberry-600x399.jpg","DeSTOvbleSe9LqctFKv8gw==":"blueberry-600x401.jpg","d9d5fyocP9DqWVSzl3W2FQ==":"raspberry-600x900.jpg","QidK6bl0Flp9jvSSciqh6g==":"blackberry-1200x800.jpg","NK9of6BZc5VsovfajwCgdA==":"kvbackground-1920x1080.png","UEO8O1oKgduUwR/ttDM8KA==":"gokucha-432x1521.png","BE1rUXtvb6OdeacSj1LzIg==":"bag-432x772.png"}